thoughtscript/__init__.py
thoughtscript/jtools1.py
thoughtscript/jtools2.py
thoughtscript-0.0.1.dist-info/LICENSE
thoughtscript-0.0.1.dist-info/METADATA
thoughtscript-0.0.1.dist-info/WHEEL
thoughtscript-0.0.1.dist-info/top_level.txt
thoughtscript-0.0.1.dist-info/RECORD
