Metadata-Version: 2.1
Name: thoughtscript
Version: 0.0.1
Summary: Short Description
Home-page: https://github.com/jrolf/rolfdog
Author: James A. Rolfsen
Author-email: james@think.dev
Classifier: Programming Language :: Python :: 3.12
Classifier: License :: OSI Approved :: MIT License
Classifier: Operating System :: OS Independent
Classifier: Natural Language :: English
Classifier: Topic :: Software Development :: Libraries :: Python Modules
License-File: LICENSE
Requires-Dist: numpy >=1.1.1
Requires-Dist: pandas >=0.1.1
